Metadata-Version: 2.1
Name: next1api
Version: 0.4.0
Summary: Next1msuic Api
Home-page: https://github.com/ali-khalse/next1api
Author: Sudo Khalse
Author-email: wwwwwq37@gmail.com
License: MIT
Download-URL: https://github.com//ali-khalse/next1api/archive/refs/heads/main.zip
Keywords: music,موزیک,next1,api
Platform: UNKNOWN
License-File: LICENSE
